{
    "metadata": {
        "author": "Raqib",
        "updated": "2026-03-31"
    },
    "data": [
        {
            "name": [
                {
                    "ar": "غات"
                }
            ],
            "latitude": 24.9626299,
            "longitude": 10.1797167,
            "id": 1
        },
        {
            "name": [
                {
                    "ar": "أوباري"
                }
            ],
            "latitude": 26.5909391,
            "longitude": 12.7695658,
            "id": 2
        },
        {
            "name": [
                {
                    "ar": "مدينة جرمة"
                }
            ],
            "latitude": 26.5284969,
            "longitude": 13.0696338,
            "id": 3
        },
        {
            "name": [
                {
                    "ar": "الغريفة"
                }
            ],
            "latitude": 26.5258867,
            "longitude": 13.0099491,
            "id": 4
        },
        {
            "name": [
                {
                    "ar": "مرزق"
                }
            ],
            "latitude": 25.9140852,
            "longitude": 13.9197199,
            "id": 5
        },
        {
            "name": [
                {
                    "ar": "سبها"
                }
            ],
            "latitude": 27.0364864,
            "longitude": 14.4290398,
            "id": 6
        },
        {
            "name": [
                {
                    "ar": "غدامس"
                }
            ],
            "latitude": 30.1258404,
            "longitude": 9.4900658,
            "id": 7
        },
        {
            "name": [
                {
                    "ar": "نالوت"
                }
            ],
            "latitude": 31.8637865,
            "longitude": 10.9827903,
            "id": 8
        },
        {
            "name": [
                {
                    "ar": "ترهونة"
                }
            ],
            "latitude": 32.4345861,
            "longitude": 13.6350687,
            "id": 9
        },
        {
            "name": [
                {
                    "ar": "الخمس"
                }
            ],
            "latitude": 32.652183,
            "longitude": 14.26801,
            "id": 10
        },
        {
            "name": [
                {
                    "ar": "الزاوية"
                }
            ],
            "latitude": 32.7596665,
            "longitude": 12.7355967,
            "id": 11
        },
        {
            "name": [
                {
                    "ar": "زوارة"
                }
            ],
            "latitude": 32.9327858,
            "longitude": 12.0806069,
            "id": 12
        },
        {
            "name": [
                {
                    "ar": "إجدابيا"
                }
            ],
            "latitude": 30.7549616,
            "longitude": 20.2233582,
            "id": 13
        },
        {
            "name": [
                {
                    "ar": "طبرق"
                }
            ],
            "latitude": 32.0773764,
            "longitude": 23.9599988,
            "id": 14
        },
        {
            "name": [
                {
                    "ar": "البيضاء"
                }
            ],
            "latitude": 32.7609529,
            "longitude": 21.7577175,
            "id": 15
        },
        {
            "name": [
                {
                    "ar": "درنة"
                }
            ],
            "latitude": 32.7593795,
            "longitude": 22.6383195,
            "id": 16
        },
        {
            "name": [
                {
                    "ar": "سرت"
                }
            ],
            "latitude": 31.2059625,
            "longitude": 16.5836206,
            "id": 17
        },
        {
            "name": [
                {
                    "ar": "صرمان"
                }
            ],
            "latitude": 32.7549766,
            "longitude": 12.5743485,
            "id": 18
        },
        {
            "name": [
                {
                    "ar": "القطرون"
                }
            ],
            "latitude": 24.8894679,
            "longitude": 14.5315003,
            "id": 19
        },
        {
            "name": [
                {
                    "ar": "مسلاتة المركز"
                }
            ],
            "latitude": 32.579922,
            "longitude": 14.0417371,
            "id": 20
        },
        {
            "name": [
                {
                    "ar": "المرج"
                }
            ],
            "latitude": 32.4853167,
            "longitude": 20.832738,
            "id": 21
        },
        {
            "name": [
                {
                    "ar": "جالو"
                }
            ],
            "latitude": 29.0331149,
            "longitude": 21.5482209,
            "id": 22
        },
        {
            "name": [
                {
                    "ar": "بني وليد"
                }
            ],
            "latitude": 31.7584309,
            "longitude": 14.0146898,
            "id": 23
        },
        {
            "name": [
                {
                    "ar": "العجيلات"
                }
            ],
            "latitude": 32.7577581,
            "longitude": 12.3773801,
            "id": 24
        },
        {
            "name": [
                {
                    "ar": "رقدالين"
                }
            ],
            "latitude": 32.8863864,
            "longitude": 11.9870728,
            "id": 25
        },
        {
            "name": [
                {
                    "ar": "زلطن"
                }
            ],
            "latitude": 32.9461461,
            "longitude": 11.866804,
            "id": 26
        },
        {
            "name": [
                {
                    "ar": "زليتن"
                }
            ],
            "latitude": 32.467562,
            "longitude": 14.56564,
            "id": 27
        },
        {
            "name": [
                {
                    "ar": "هون"
                }
            ],
            "latitude": 29.1245649,
            "longitude": 15.9402605,
            "id": 28
        },
        {
            "name": [
                {
                    "ar": "الزهراء"
                }
            ],
            "latitude": 32.6780313,
            "longitude": 12.8725109,
            "id": 29
        },
        {
            "name": [
                {
                    "ar": "ودان"
                }
            ],
            "latitude": 29.1613826,
            "longitude": 16.141311,
            "id": 30
        },
        {
            "name": [
                {
                    "ar": "بنغازي"
                }
            ],
            "latitude": 32.1200168,
            "longitude": 20.0812174,
            "id": 31
        },
        {
            "name": [
                {
                    "ar": "الأبيار"
                }
            ],
            "latitude": 32.1896453,
            "longitude": 20.5945086,
            "id": 32
        },
        {
            "name": [
                {
                    "ar": "الأصابعة"
                }
            ],
            "latitude": 32.0351904,
            "longitude": 12.8719462,
            "id": 33
        },
        {
            "name": [
                {
                    "ar": "غريان"
                }
            ],
            "latitude": 32.1715873,
            "longitude": 13.0211451,
            "id": 34
        },
        {
            "name": [
                {
                    "ar": "قصر بن غشير"
                }
            ],
            "latitude": 32.6859736,
            "longitude": 13.1764996,
            "id": 35
        },
        {
            "name": [
                {
                    "ar": "طرابلس"
                }
            ],
            "latitude": 32.896672,
            "longitude": 13.1777923,
            "id": 36
        },
        {
            "name": [
                {
                    "ar": "العزيزية"
                }
            ],
            "latitude": 32.5330923,
            "longitude": 13.0176242,
            "id": 37
        },
        {
            "name": [
                {
                    "ar": "الرحيبات"
                }
            ],
            "latitude": 31.8836726,
            "longitude": 11.8986142,
            "id": 38
        },
        {
            "name": [
                {
                    "ar": "مصراتة"
                }
            ],
            "latitude": 32.3745923,
            "longitude": 15.0905803,
            "id": 39
        }
    ]
}